imitatio_ostendendi/__init__.py
imitatio_ostendendi/constants.py
imitatio_ostendendi/widgets.py
imitatio_ostendendi/widgets/__init__.py
imitatio_ostendendi/widgets/base.py
imitatio_ostendendi/widgets/buttons.py
imitatio_ostendendi/widgets/entry.py
imitatio_ostendendi/widgets/frames.py
imitatio_ostendendi/widgets/text.py
tests/__init__.py
tests/run_tests.py
tests/test_base_widget.py
tests/test_button_widget.py
tests/test_entry_widget.py
tests/test_frame_widget.py
tests/test_text_widget.py
imitatio_ostendendi-0.2.0.dist-info/LICENSE
imitatio_ostendendi-0.2.0.dist-info/METADATA
imitatio_ostendendi-0.2.0.dist-info/WHEEL
imitatio_ostendendi-0.2.0.dist-info/top_level.txt
imitatio_ostendendi-0.2.0.dist-info/RECORD
